alembic_multischema/__init__.py
alembic_multischema-0.0.7.dist-info/LICENSE
alembic_multischema-0.0.7.dist-info/METADATA
alembic_multischema-0.0.7.dist-info/WHEEL
alembic_multischema-0.0.7.dist-info/top_level.txt
alembic_multischema-0.0.7.dist-info/RECORD
