Metadata-Version: 2.1
Name: alembic-multischema
Version: 0.0.7
Summary: Multi schema postgres migrations using alembic
Home-page: https://github.com/QuiNovas/alembic-multischema
Author: Mathew Moon
Author-email: me@mathewmoon.net
License: APL 2.0
Keywords: quinovas
Platform: UNKNOWN
Classifier: Development Status :: 3 - Alpha
Classifier: Topic :: System :: Software Distribution
Classifier: Intended Audience :: Developers
Classifier: License :: OSI Approved :: Apache Software License
Classifier: Programming Language :: Python :: 3.7
